fermentomap/__init__.py
fermentomap/core.py
fermentomap/parser.py
fermentomap-0.1.0.dist-info/licenses/LICENSE
fermentomap-0.1.0.dist-info/METADATA
fermentomap-0.1.0.dist-info/WHEEL
fermentomap-0.1.0.dist-info/top_level.txt
fermentomap-0.1.0.dist-info/RECORD
